google/cloud/spanner.py
google/cloud/spanner_admin_database_v1/__init__.py
google/cloud/spanner_admin_database_v1/gapic_metadata.json
google/cloud/spanner_admin_database_v1/gapic_version.py
google/cloud/spanner_admin_database_v1/py.typed
google/cloud/spanner_admin_database_v1/services/__init__.py
google/cloud/spanner_admin_database_v1/services/database_admin/__init__.py
google/cloud/spanner_admin_database_v1/services/database_admin/async_client.py
google/cloud/spanner_admin_database_v1/services/database_admin/client.py
google/cloud/spanner_admin_database_v1/services/database_admin/pagers.py
google/cloud/spanner_admin_database_v1/services/database_admin/transports/__init__.py
google/cloud/spanner_admin_database_v1/services/database_admin/transports/base.py
google/cloud/spanner_admin_database_v1/services/database_admin/transports/grpc.py
google/cloud/spanner_admin_database_v1/services/database_admin/transports/grpc_asyncio.py
google/cloud/spanner_admin_database_v1/services/database_admin/transports/rest.py
google/cloud/spanner_admin_database_v1/services/database_admin/transports/rest_base.py
google/cloud/spanner_admin_database_v1/types/__init__.py
google/cloud/spanner_admin_database_v1/types/backup.py
google/cloud/spanner_admin_database_v1/types/backup_schedule.py
google/cloud/spanner_admin_database_v1/types/common.py
google/cloud/spanner_admin_database_v1/types/spanner_database_admin.py
google/cloud/spanner_admin_instance_v1/__init__.py
google/cloud/spanner_admin_instance_v1/gapic_metadata.json
google/cloud/spanner_admin_instance_v1/gapic_version.py
google/cloud/spanner_admin_instance_v1/py.typed
google/cloud/spanner_admin_instance_v1/services/__init__.py
google/cloud/spanner_admin_instance_v1/services/instance_admin/__init__.py
google/cloud/spanner_admin_instance_v1/services/instance_admin/async_client.py
google/cloud/spanner_admin_instance_v1/services/instance_admin/client.py
google/cloud/spanner_admin_instance_v1/services/instance_admin/pagers.py
google_cloud_spanner-3.55.0.dist-info/LICENSE
google_cloud_spanner-3.55.0.dist-info/METADATA
google_cloud_spanner-3.55.0.dist-info/WHEEL
google_cloud_spanner-3.55.0.dist-info/top_level.txt
google_cloud_spanner-3.55.0.dist-info/RECORD
